pref_voting/__init__.py
pref_voting/analysis.py
pref_voting/axiom.py
pref_voting/axiom_helpers.py
pref_voting/axioms.py
pref_voting/c1_methods.py
pref_voting/combined_methods.py
pref_voting/create_methods.py
pref_voting/data/examples/condorcet_winner/minimal_Anti-Plurality.soc
pref_voting/data/examples/condorcet_winner/minimal_Borda.soc
pref_voting/data/examples/condorcet_winner/minimal_Bracket_Voting.soc
pref_voting/data/examples/condorcet_winner/minimal_Bucklin.soc
pref_voting/data/examples/condorcet_winner/minimal_Coombs.soc
pref_voting/data/examples/condorcet_winner/minimal_Coombs_PUT.soc
pref_voting/data/examples/condorcet_winner/minimal_Coombs_TB.soc
pref_voting/data/examples/condorcet_winner/minimal_Dowdall.soc
pref_voting/data/examples/condorcet_winner/minimal_Instant_Runoff.soc
pref_voting/data/examples/condorcet_winner/minimal_Instant_Runoff_PUT.soc
pref_voting/data/examples/condorcet_winner/minimal_Instant_Runoff_TB.soc
pref_voting/data/examples/condorcet_winner/minimal_Iterated_Removal_Condorcet_Loser.soc
pref_voting/data/examples/condorcet_winner/minimal_Pareto.soc
pref_voting/data/examples/condorcet_winner/minimal_Plurality.soc
pref_voting/data/examples/condorcet_winner/minimal_PluralityWRunoff_PUT.soc
pref_voting/data/examples/condorcet_winner/minimal_Positive-Negative_Voting.soc
pref_voting/data/examples/condorcet_winner/minimal_Simplified_Bucklin.soc
pref_voting/data/examples/condorcet_winner/minimal_Superior_Voting.soc
pref_voting/data/examples/condorcet_winner/minimal_Weighted_Bucklin.soc
pref_voting/data/examples/condorcet_winner/minimal_resolute_Anti-Plurality.soc
pref_voting/data/examples/condorcet_winner/minimal_resolute_Borda.soc
pref_voting/data/examples/condorcet_winner/minimal_resolute_Bracket_Voting.soc
pref_voting/data/examples/condorcet_winner/minimal_resolute_Bucklin.soc
pref_voting/data/examples/condorcet_winner/minimal_resolute_Coombs.soc
pref_voting/data/examples/condorcet_winner/minimal_resolute_Coombs_PUT.soc
pref_voting-1.17.6.dist-info/METADATA
pref_voting-1.17.6.dist-info/WHEEL
pref_voting-1.17.6.dist-info/licenses/LICENSE.txt
pref_voting-1.17.6.dist-info/RECORD
