Metadata-Version: 2.4
Name: pref_voting
Version: 1.17.6
Summary: pref_voting is a Python package that contains tools to reason about elections and margin graphs, and implementations of voting methods.
License: MIT
License-File: LICENSE.txt
Author: Eric Pacuit
Author-email: epacuit@umd.edu
Requires-Python: >=3.10,<4.0
Classifier: License :: OSI Approved :: MIT License
Classifier: Programming Language :: Python :: 3
Classifier: Programming Language :: Python :: 3.10
Classifier: Programming Language :: Python :: 3.11
Classifier: Programming Language :: Python :: 3.12
Classifier: Programming Language :: Python :: 3.13
Classifier: Programming Language :: Python :: 3.14
Requires-Dist: filelock (>=3.12.2,<4.0.0)
Requires-Dist: matplotlib (>=3.5.2,<4.0.0)
Requires-Dist: nashpy (>=0.0.40,<0.0.41)
Requires-Dist: networkx (>=3.0,<4.0)
Requires-Dist: numba (>=0.61.0,<0.62.0)
Requires-Dist: ortools (>=9.8.0,<10.0.0)
Requires-Dist: pathos (>=0.3.3,<0.4.0)
Requires-Dist: preflibtools (>=2.0.22,<3.0.0)
Requires-Dist: prefsampling (>=0.1.16,<0.2.0)
Requires-Dist: random2 (>=1.0.1,<2.0.0)
Requires-Dist: scipy (>=1.0.0,<2.0.0)
Requires-Dist: seaborn (>=0.13.2,<0.14.0)
Requires-Dist: tabulate (>=0.9.0,<0.10.0)
Project-URL: Homepage, https://github.com/voting-tools/pref_voting
Project-URL: Repository, https://github.com/voting-tools/pref_voting
